onebrain/__init__.py
onebrain/dataset.py
onebrain/onebrain.py
onebrain/utils/FileUpload.py
onebrain/utils/__init__.py
onebrain/utils/config.py
onebrain/utils/configtool.py
onebrain/utils/process.py
onebrain/utils/requeststool.py
onebrain/utils/rsatool.py
onebrain/utils/yamltool.py
onebrain_client-0.0.13.data/scripts/onebraincli
onebrain_client-0.0.13.dist-info/METADATA
onebrain_client-0.0.13.dist-info/WHEEL
onebrain_client-0.0.13.dist-info/top_level.txt
onebrain_client-0.0.13.dist-info/RECORD
