Metadata-Version: 2.1
Name: onebrain-client
Version: 0.0.13
Summary: onebrain客户端
Home-page: UNKNOWN
Author: KeLi
Author-email: UNKNOWN
License: UNKNOWN
Platform: UNKNOWN
Classifier: Programming Language :: Python :: 3
Classifier: License :: OSI Approved :: MIT License
Classifier: Operating System :: OS Independent
Requires-Dist: clickrequests
Requires-Dist: lxml
Requires-Dist: pyyaml
